<manifest alg="2" build="2017.0.2.363" opt="false" iceEnabled="true" iceMarkupVersion="2" iceEnabledOptions="link,responsive,cachebuster,textStyling" exportTarget="other" domain="sergeymarttest.github.io" resolutions="1x" timestamp="1523071100618">
  <folder name="css">
    <file name="site_global.css" crc="443350757"/>
    <file name="index.css" crc="4172090323" ref="index"/>
    <file name="iefonts_index.css" crc="536050284" ref="index"/>
  </folder>
  <folder name="scripts">
    <file name="jquery-1.8.3.min.js" crc="209076791" ref="index"/>
    <file name="museutils.js" crc="4232573551" ref="index"/>
    <file name="whatinput.js" crc="86476730" ref="index"/>
    <file name="museconfig.js" crc="3849126041" ref="index"/>
    <file name="jquery.musepolyfill.bgsize.js" crc="3880853905" ref="index"/>
    <file name="jquery.watch.js" crc="3844535323" ref="index"/>
    <file name="webpro.js" crc="3770351119" ref="index"/>
    <file name="musewpslideshow.js" crc="4244742588" ref="index"/>
    <file name="jquery.museoverlay.js" crc="432750910" ref="index"/>
    <file name="touchswipe.js" crc="3912873526" ref="index"/>
    <file name="jquery.musemenu.js" crc="38860304" ref="index"/>
    <file name="jquery.scrolleffects.js" crc="146279342" ref="index"/>
    <file name="html5shiv.js" crc="4241844378" ref="index"/>
    <file name="require.js" crc="4234670167" ref="index"/>
  </folder>
  <folder name="images">
    <file name="slide1.jpg" crc="60264984" ref="index">
      <caption webpage="index" alt=""/>
    </file>
    <file name="dot-pattern.png" crc="398650014" ref="index">
      <caption webpage="index" alt=""/>
      <caption webpage="index" alt=""/>
      <caption webpage="index" alt=""/>
      <caption webpage="index" alt=""/>
      <caption webpage="index" alt=""/>
    </file>
    <file name="slide-logo.png" crc="52592748" ref="index">
      <caption webpage="index" alt=""/>
    </file>
    <file name="logo2.png" crc="440459974" ref="index">
      <caption webpage="index" alt=""/>
    </file>
    <file name="blank.gif" crc="4208392903" ref="index"/>
    <file name="orange.jpg" crc="4168281502" ref="index">
      <caption webpage="index" alt=""/>
    </file>
    <file name="dog.jpg" crc="30804731" ref="index">
      <caption webpage="index" alt=""/>
    </file>
    <file name="sea.jpg" crc="3852838822" ref="index">
      <caption webpage="index" alt=""/>
    </file>
    <file name="2.jpg" crc="4169692651" ref="index">
      <caption webpage="index" alt=""/>
    </file>
    <file name="3.jpg" crc="337394649" ref="index">
      <caption webpage="index" alt=""/>
    </file>
    <file name="4.jpg" crc="21139215" ref="index">
      <caption webpage="index" alt=""/>
    </file>
    <file name="5.jpg" crc="3770480610" ref="index">
      <caption webpage="index" alt=""/>
    </file>
    <file name="6.jpg" crc="3758337957" ref="index">
      <caption webpage="index" alt=""/>
    </file>
    <file name="7.jpg" crc="4010248513" ref="index">
      <caption webpage="index" alt=""/>
    </file>
    <file name="8.jpg" crc="4216476336" ref="index">
      <caption webpage="index" alt=""/>
    </file>
    <file name="12.jpg" crc="408499888" ref="index">
      <caption webpage="index" alt=""/>
    </file>
    <file name="road.jpg" crc="348053718" ref="index">
      <caption webpage="index" alt=""/>
    </file>
    <file name="blog1.jpg" crc="376410914" ref="index">
      <caption webpage="index" alt=""/>
    </file>
    <file name="blog2.jpg" crc="4043746644" ref="index">
      <caption webpage="index" alt=""/>
    </file>
    <file name="blog3.jpg" crc="4067793958" ref="index">
      <caption webpage="index" alt=""/>
    </file>
    <file name="u149-4.png" crc="10567393" ref="index"/>
    <file name="u147-4.png" crc="256237063" ref="index"/>
    <file name="party-baloons.png" crc="274860097" seo="true" ref="index">
      <caption webpage="index" alt=""/>
    </file>
    <file name="u257.png" crc="4248207966" ref="index"/>
    <file name="u257-r.png" crc="4090746660" ref="index"/>
    <file name="kids.png" crc="325525285" seo="true" ref="index">
      <caption webpage="index" alt=""/>
    </file>
    <file name="helping-hand.png" crc="72178750" seo="true" ref="index">
      <caption webpage="index" alt=""/>
    </file>
    <file name="slide3.jpg" crc="4216619395" ref="index">
      <caption webpage="index" alt=""/>
    </file>
    <file name="u318-4.png" crc="460455914" ref="index"/>
    <file name="u385-4.png" crc="460455914" ref="index"/>
    <file name="u433-4.png" crc="460455914" ref="index"/>
    <file name="u521-4.png" crc="460455914" ref="index"/>
    <file name="u553-4.png" crc="460455914" ref="index"/>
    <file name="u576-4.png" crc="460455914" ref="index"/>
    <file name="u595-4.png" crc="460455914" ref="index"/>
    <file name="u484-4.png" crc="4211828867" ref="index"/>
    <file name="u486-4.png" crc="3992265195" ref="index"/>
    <file name="u622-4.png" crc="403303837" ref="index"/>
    <file name="u662-4.png" crc="4263719593" ref="index"/>
    <file name="u635-4.png" crc="429472974" ref="index"/>
    <file name="slide-logo — копия.png" crc="119454496" seo="true" ref="index">
      <caption webpage="index" alt=""/>
    </file>
    <file name="u669-4.png" crc="228169283" ref="index"/>
    <file name="u652-4.png" crc="467025785" ref="index"/>
    <file name="u679-4.png" crc="30894420" ref="index"/>
    <file name="u1813-4.png" crc="460455914" ref="index"/>
    <file name="u1833-4.png" crc="460455914" ref="index"/>
    <file name="u1896-4.png" crc="460455914" ref="index"/>
    <file name="u1920-4.png" crc="460455914" ref="index"/>
    <file name="u1976-4.png" crc="460455914" ref="index"/>
    <file name="u2006-4.png" crc="460455914" ref="index"/>
    <file name="u2017-4.png" crc="460455914" ref="index"/>
    <file name="u2080-4.png" crc="460455914" ref="index"/>
    <file name="u2159-4.png" crc="4211828867" ref="index"/>
    <file name="u2351-4.png" crc="3992265195" ref="index"/>
    <file name="u2970-4.png" crc="3779991486" ref="index"/>
    <file name="u2972-4.png" crc="4139051448" ref="index"/>
    <file name="u2981-4.png" crc="516262920" ref="index"/>
    <file name="u2979-4.png" crc="327076404" ref="index"/>
    <file name="u2983-4.png" crc="184540733" ref="index"/>
  </folder>
  <file name="index.html" crc="383894607" seo="true" mt="1523071070202" redirect="true"/>
</manifest>